protex/__init__.py
protex/__main__.py
protex/ast.py
protex/cli.py
protex/commands.json
protex/commands.py
protex/lexer.py
protex/parser.py
protex/text_pos.py
protex-0.1.0.data/scripts/protex
protex-0.1.0.dist-info/LICENSE
protex-0.1.0.dist-info/METADATA
protex-0.1.0.dist-info/WHEEL
protex-0.1.0.dist-info/top_level.txt
protex-0.1.0.dist-info/RECORD
