Metadata-Version: 2.1
Name: protex
Version: 0.1.0
Summary: Clean Latex sources without loosing track of positions
Home-page: UNKNOWN
Author: Théo (Lattay) Cavignac
Author-email: theo.cavignac@gmail.com
License: MIT
Platform: UNKNOWN
